setup.py
flask_checkargs/__init__.py
flask_checkargs/checkargs.py
flask_checkargs.egg-info/PKG-INFO
flask_checkargs.egg-info/SOURCES.txt
flask_checkargs.egg-info/dependency_links.txt
flask_checkargs.egg-info/not-zip-safe
flask_checkargs.egg-info/top_level.txt