Metadata-Version: 1.1
Name: flask-checkargs
Version: 0.1.2
Summary: A module to simplify checking arguments in Flask apps
Home-page: http://www.github.com/jsevilleja/flask_checkargs
Author: Joel Sevilleja
Author-email: joel@jsevilleja.org
License: MIT
Platform: UNKNOWN
Classifier: Development Status :: 4 - Beta
Classifier: Intended Audience :: Developers
Classifier: Intended Audience :: System Administrators
Classifier: License :: OSI Approved :: MIT License
Classifier: Programming Language :: Python
Classifier: Topic :: Security
Classifier: Topic :: Software Development :: Libraries :: Python Modules
Requires: flask
